topogmesh/__init__.py
topogmesh/cli.py
topogmesh/export.py
topogmesh/geo_utils.py
topogmesh/hm_utils.py
topogmesh/mesh.py
topogmesh/mesh_generator.py
topogmesh/webscraper.py
topogmesh-0.1.7.dist-info/licenses/LICENCE
topogmesh-0.1.7.dist-info/licenses/NOTICE
topogmesh-0.1.7.dist-info/METADATA
topogmesh-0.1.7.dist-info/WHEEL
topogmesh-0.1.7.dist-info/entry_points.txt
topogmesh-0.1.7.dist-info/top_level.txt
topogmesh-0.1.7.dist-info/RECORD
