Metadata-Version: 2.4
Name: topogmesh
Version: 0.1.7
Summary: Generate 3D print files from .tif files
Author-email: Finley Stirk <fs618@cam.ac.uk>
License: MIT
Classifier: License :: OSI Approved :: MIT License
Classifier: Programming Language :: Python :: 3
Classifier: Operating System :: OS Independent
Requires-Python: >=3.9
License-File: LICENCE
License-File: NOTICE
Requires-Dist: lib3mf
Requires-Dist: numpy
Requires-Dist: gdal
Requires-Dist: yirgacheffe
Requires-Dist: scikit-image
Requires-Dist: osmnx
Requires-Dist: requests
Dynamic: license-file
